[{"deck":"c-doctorwho","icon":"stethoscope","text":"Fish fingering your custard.","id":"wh-M5HdN4P9yCZG"},{"deck":"c-doctorwho","icon":"stethoscope","text":"The hideousness that is Raxacoricofallapatorious.","id":"wh-pOtWzrJyjHgS"},{"deck":"c-doctorwho","icon":"stethoscope","text":"An Ood getting a starring role in a hentai.","id":"wh-jKYco8RX8S9z"},{"deck":"c-doctorwho","icon":"stethoscope","text":"Christopher Eccleston.","id":"wh-X42nmpXd68OS"},{"deck":"c-doctorwho","icon":"stethoscope","text":"Matt Smith.","id":"wh-RjCw1WW7GBSp"},{"deck":"c-doctorwho","icon":"stethoscope","text":"A kid in a gas mask asking if you are his mummy.","id":"wh-Vg6d9M88OuGK"},{"deck":"c-doctorwho","icon":"stethoscope","text":"Siltheen farts.","id":"wh-Mc3SvjV3CSwH"},{"deck":"c-doctorwho","icon":"stethoscope","text":"The big banana in your pocket.","id":"wh-4uDLOmgTTCma"},{"deck":"c-doctorwho","icon":"stethoscope","text":"Taking a Doctor Poo.","id":"wh-MLouZcDQMr9P"},{"deck":"c-doctorwho","icon":"stethoscope","text":"David Tennant.","id":"wh-mWkcdbMSXviI"},{"deck":"c-doctorwho","icon":"stethoscope","text":"Low-budget special effects.","id":"wh-RFyFxKS766Lg"},{"deck":"c-doctorwho","icon":"stethoscope","text":"River Song.","id":"wh-oi8wVNABOhA0"},{"deck":"c-doctorwho","icon":"stethoscope","text":"Dalek porn.","id":"wh-Xo2whSvwawaB"},{"deck":"c-doctorwho","icon":"stethoscope","text":"Eggs.","id":"wh-LOc3Gd07Via2"},{"deck":"c-doctorwho","icon":"stethoscope","text":"Finding Autons oddly attractive.","id":"wh-mfHKFXOBnELS"},{"deck":"c-doctorwho","icon":"stethoscope","text":"THE END OF TIME ITSELF!","id":"wh-H0pk5HMSAJPm"},{"deck":"c-doctorwho","icon":"stethoscope","text":"Glenn Beck convulsively puking as a brood of Daleks swarm in on him.","id":"wh-jyLiHZEUXjqP"},{"deck":"c-doctorwho","icon":"stethoscope","text":"The fuck machine dungeon of the Cybermen.","id":"wh-o4zhJVEG410r"},{"deck":"c-doctorwho","icon":"stethoscope","text":"Fifty years of fanfic.","id":"wh-l7yTmaVC1H77"},{"deck":"c-doctorwho","icon":"stethoscope","text":"Just now realizing Torchwood is an anagram of Doctor Who.","id":"wh-VvGcHVXrcOn8"},{"deck":"c-doctorwho","icon":"stethoscope","text":"The Doctor going back in time to solve a REAL problem: Twilight.","id":"wh-pQhKDFmCs8jj"},{"deck":"c-doctorwho","icon":"stethoscope","text":"The Silence.","id":"wh-l5AJzhJXlJdV"},{"deck":"c-doctorwho","icon":"stethoscope","text":"A Doctor Who body pillow.","id":"wh-SlFtDwcMNaQ6"},{"deck":"c-doctorwho","icon":"stethoscope","text":"A Rusty Cyberman.","id":"wh-V0HZFiP4VPr5"},{"deck":"c-doctorwho","icon":"stethoscope","text":"Drunkenly drawing tally marks on your face.","id":"wh-o3AfRYezVAOE"},{"deck":"c-doctorwho","icon":"stethoscope","text":"The Doctor having a chance encounter with a couple of 80s metalheads.","id":"wh-d6GmjWAQzySa"},{"deck":"c-doctorwho","icon":"stethoscope","text":"A shitty Doctor Who knock-knock joke.","id":"wh-3DwkO0DFyEYy"},{"deck":"c-doctorwho","icon":"stethoscope","text":"The Master, baiting the Doctor into a trap.","id":"wh-9o7dNfOhGXt0"},{"deck":"c-doctorwho","icon":"stethoscope","text":"Davros getting up on the wrong side of the bed.","id":"wh-aAGWdjR2oQsd"},{"deck":"c-doctorwho","icon":"stethoscope","text":"Wishing you could regenerate.","id":"wh-UdiVejavW3TV"},{"deck":"c-doctorwho","icon":"stethoscope","text":"A Vashta Nerada that just wants a hug.","id":"wh-FzPCRiY7bsKq"},{"deck":"c-doctorwho","icon":"stethoscope","text":"The poor costume decisions that were the 1970s.","id":"wh-ZR84NHv1RkDQ"},{"deck":"c-doctorwho","icon":"stethoscope","text":"Kidnapping a barely-legal woman to time travel with.","id":"wh-mkMdsDdaZaPI"},{"deck":"c-doctorwho","icon":"stethoscope","text":"Tom Baker, in nothing but a scarf.","id":"wh-8W8gEVnAWDea"},{"deck":"c-doctorwho","icon":"stethoscope","text":"Walking in on Jack Harkness doing your mom. And your dad.","id":"wh-57zHVjZsYJY1"},{"deck":"c-doctorwho","icon":"stethoscope","text":"The buzzing noise the Sonic Screwdriver makes.","id":"wh-DCxAcbjQdeEC"},{"deck":"c-doctorwho","icon":"stethoscope","text":"Sharing a public restroom with a Weeping Angel.","id":"wh-cb9oGibP7ufk"},{"deck":"c-doctorwho","icon":"stethoscope","text":"A bigger, bluer TARDIS.","id":"wh-vUWZsbY4jd49"},{"deck":"c-doctorwho","icon":"stethoscope","text":"K-9 humping your leg.","id":"wh-ReTu0lDyftVU"},{"deck":"c-doctorwho","icon":"stethoscope","text":"The Master singing Bad Case of Loving You.","id":"wh-gPxFWTZiYjqN"},{"deck":"c-doctorwho","icon":"stethoscope","text":"Rose Tyler's teeth.","id":"wh-Yz3e3sKe1tKv"},{"deck":"c-doctorwho","icon":"stethoscope","text":"A GUITARDIS.","id":"wh-ESNsKSEsKOyK"},{"deck":"c-doctorwho","icon":"stethoscope","text":"A fez caked with semen.","id":"wh-9KNOvwyKxeXR"},{"deck":"c-doctorwho","icon":"stethoscope","text":"Robot Anne Robinson.","id":"wh-hJwA5kHNT3jY"},{"deck":"c-doctorwho","icon":"stethoscope","text":"Steven Moffatt taking a big old dump in your Cheerios.","id":"wh-oXIn0DCIvDYx"},{"deck":"c-doctorwho","icon":"stethoscope","text":"Fapping to Billie Piper portraying a callgirl.","id":"wh-F8kPWkzhZ5N4"},{"deck":"c-doctorwho","icon":"stethoscope","text":"Captain Jack Harkness.","id":"wh-WEjo4PyrUSD3"},{"deck":"c-doctorwho","icon":"stethoscope","text":"The Celestial Toymaker's plaything.","id":"wh-zmMeKletPDn0"},{"deck":"c-doctorwho","icon":"stethoscope","text":"A Costco-sized bag of Jelly Babies.","id":"wh-fdeta8tm8PAr"},{"deck":"c-doctorwho","icon":"stethoscope","text":"Being used as a plot device by Steven Moffat.","id":"wh-AqXeUkkQUgnU"},{"deck":"c-doctorwho","icon":"stethoscope","text":"A furry writing BAD WOLF everywhere.","id":"wh-x9hAzTxnEmuv"},{"deck":"c-doctorwho","icon":"stethoscope","text":"The Mary Jane Adventures.","id":"wh-77C0xcUjq42t"},{"deck":"c-doctorwho","icon":"stethoscope","text":"Sixteen feet of scarf bondage.","id":"wh-nC6DVeGcHMeG"},{"deck":"c-doctorwho","icon":"stethoscope","text":"Getting so much plastic surgery you have to be framed and moisturized.","id":"wh-6PuB30lw37lo"},{"deck":"c-doctorwho","icon":"stethoscope","text":"Slipping her the ol' plastic Mickey.","id":"wh-jQ3oJCIf2BWq"},{"deck":"c-doctorwho","icon":"stethoscope","text":"Fondling a Dalek's slippery bits.","id":"wh-NXwLYfMlQoYF"},{"deck":"c-doctorwho","icon":"stethoscope","text":"Air from my lungs.","id":"wh-40Gi8CyiPyzG"},{"deck":"c-doctorwho","icon":"stethoscope","text":"A Sonic Screwdriver stuck on the vibrate setting.","id":"wh-VHWQgLFK7aYQ"},{"deck":"c-doctorwho","icon":"stethoscope","text":"Pouting in a rain storm and having to take a wicked piss.","id":"wh-hIbju61PUKek"},{"deck":"c-doctorwho","icon":"stethoscope","text":"Companion Porn.","id":"wh-TIiiuX2synEa"},{"deck":"c-doctorwho","icon":"stethoscope","text":"An acid rain shower on Skaro.","id":"wh-z0Id2qOuH16M"},{"deck":"c-doctorwho","icon":"stethoscope","text":"Plot holes so wide you could drive a truck through them.","id":"wh-uflyzmgsSph6"},{"deck":"c-doctorwho","icon":"stethoscope","text":"A blinged out TARDIS blasting dubstep when it is traveling.","id":"wh-VL0bm5mtWnKk"},{"deck":"c-doctorwho","icon":"stethoscope","text":"The poor decision that is having a staring contest with a weeping angel.","id":"wh-V4Dw3QiKO55P"}]