[{"pick":1,"deck":"CAHe2","text":"During his midlife crisis, my dad got really into ______.","icon":"2","id":"bl-syDX"},{"pick":1,"deck":"CAHe2","text":"Before I run for president, I must destroy all evidence of my involvement with ______.","icon":"2","id":"bl-VYFO"},{"pick":1,"deck":"CAHe2","text":"My new favorite porn star is Joey \"______\" McGee.","icon":"2","id":"bl-nYRE"},{"pick":1,"deck":"CAHe2","text":"In his newest and most difficult stunt, David Blaine must escape from ______.","icon":"2","id":"bl-3qZO"},{"pick":1,"deck":"CAHe2","text":"This is your captain speaking. Fasten your seatbelts and prepare for ______.","icon":"2","id":"bl-C7Tj"},{"pick":1,"deck":"CAHe2","text":"The Five Stages of Grief: denial, anger, bargaining, ______, acceptance.","icon":"2","id":"bl-brAf"},{"pick":1,"deck":"CAHe2","text":"Little Miss Muffet\nSat on a tuffet,\nEating her curds and ______.","icon":"2","id":"bl-PczO"},{"pick":1,"deck":"CAHe2","text":"This month's Cosmo: \"Spice up your sex life by bringing ______ into the bedroom.\".","icon":"2","id":"bl-IQ4J"},{"pick":1,"deck":"CAHe2","text":"My country, 'tis of thee, sweet land of ______.","icon":"2","id":"bl-dhFP"},{"pick":1,"deck":"CAHe2","text":"Next time on Dr. Phil: How to talk to your child about ______.","icon":"2","id":"bl-65Zo"},{"pick":1,"deck":"CAHe2","text":"Only two things in life are certain: death and ______.","icon":"2","id":"bl-R77y"},{"pick":1,"deck":"CAHe2","text":"Everyone down on the ground! We don't want to hurt anyone. We're just here for ______.","icon":"2","id":"bl-MqpP"},{"pick":1,"deck":"CAHe2","text":"The healing process began when I joined a support group for victims of ______.","icon":"2","id":"bl-sB8B"},{"pick":1,"deck":"CAHe2","text":"The votes are in, and the new high school mascot is ______.","icon":"2","id":"bl-L83V"},{"pick":1,"deck":"CAHe2","text":"Charades was ruined for me forever when my mom had to act out ______.","icon":"2","id":"bl-AM9u"},{"pick":1,"deck":"CAHe2","text":"Tonight on 20/20: What you don't know about ______ could kill you.","icon":"2","id":"bl-sgLr"}]