[{"pick":1,"deck":"CAHe3","text":"Hey baby, come back to my place and I'll show you ______.","icon":"3","id":"bl-zMZB"},{"pick":1,"deck":"CAHe3","text":"My gym teacher got fired for adding ______ to the obstacle course.","icon":"3","id":"bl-a0Ll"},{"pick":1,"deck":"CAHe3","text":"Finally! A service that delivers ______ right to your door.","icon":"3","id":"bl-eKOV"},{"pick":1,"deck":"CAHe3","text":"During high school, I never really fit in until I found ______ club.","icon":"3","id":"bl-KzVE"},{"pick":1,"deck":"CAHe3","text":"Money can't buy me love, but it can buy me ______.","icon":"3","id":"bl-uyVq"},{"pick":1,"deck":"CAHe3","text":"A successful job interview begins with a firm handshake and ends with ______.","icon":"3","id":"bl-YJpN"},{"pick":1,"deck":"CAHe3","text":"Lovin' you is easy 'cause you're ______.","icon":"3","id":"bl-obX9"},{"pick":1,"deck":"CAHe3","text":"The blind date was going horribly until we discovered our shared interest in ______.","icon":"3","id":"bl-Cq8p"},{"pick":1,"deck":"CAHe3","text":"What left this stain on my couch?","icon":"3","id":"bl-IFvt"},{"pick":1,"deck":"CAHe3","text":"Turns out that ______-Man was neither the hero we needed nor wanted.","icon":"3","id":"bl-zSu9"},{"pick":1,"deck":"CAHe3","text":"In the seventh circle of Hell, sinners must endure ______ for all eternity.","icon":"3","id":"bl-0X7J"},{"pick":1,"deck":"CAHe3","text":"As part of his daily regimen, Anderson Cooper sets aside 15 minutes for ______.","icon":"3","id":"bl-zJNu"},{"pick":1,"deck":"CAHe3","text":"And what did *you* bring for show and tell?","icon":"3","id":"bl-RJs9"},{"pick":1,"deck":"CAHe3","text":"I'm not like the rest of you. I'm too rich and busy for ______.","icon":"3","id":"bl-rGEk"},{"pick":1,"deck":"CAHe3","text":"______. Awesome in theory, kind of a mess in practice.","icon":"3","id":"bl-wT9p"},{"pick":1,"deck":"CAHe3","text":"As part of his contract, Prince won't perform without ______ in his dressing room.","icon":"3","id":"bl-RgOz"}]