[{"pick":1,"deck":"crabs","text":"9-1-1, what's your emergency?","icon":"wrench","id":"bl-eA6F"},{"pick":1,"deck":"crabs","text":"______, just for a second. Just to see how it feels.","icon":"wrench","id":"bl-sVVy"},{"pick":1,"deck":"crabs","text":"______, you da real MVP.","icon":"wrench","id":"bl-Zl58"},{"pick":1,"deck":"crabs","text":"______: Ain't nobody got time for that!","icon":"wrench","id":"bl-d911"},{"pick":1,"deck":"crabs","text":"______: boil 'em, mash 'em, stick 'em in a stew!","icon":"wrench","id":"bl-N8lk"},{"pick":1,"deck":"crabs","text":"______: I volunteer as tribute!","icon":"wrench","id":"bl-7gRz"},{"pick":1,"deck":"crabs","text":"______: it's magically delicious.","icon":"wrench","id":"bl-mHjW"},{"pick":1,"deck":"crabs","text":"______: Just another way that God shows us he loves us.","icon":"wrench","id":"bl-Yy8G"},{"pick":1,"deck":"crabs","text":"______: Just girly things.","icon":"wrench","id":"bl-yXx7"},{"pick":1,"deck":"crabs","text":"______: Just sayin'.","icon":"wrench","id":"bl-uue8"},{"pick":1,"deck":"crabs","text":"______: not even once.","icon":"wrench","id":"bl-LdEi"},{"pick":1,"deck":"crabs","text":"______: Provided by the management for your protection.","icon":"wrench","id":"bl-4pBk"},{"pick":1,"deck":"crabs","text":"______: Your ideas are intriguing to me and I wish to subscribe to your newsletter.","icon":"wrench","id":"bl-wRuc"},{"pick":1,"deck":"crabs","text":"______? That's what *she* said.","icon":"wrench","id":"bl-2qTC"},{"pick":1,"deck":"crabs","text":"A new Russian dash-cam video shows ______, right there in the middle of the street!","icon":"wrench","id":"bl-iCcs"},{"pick":1,"deck":"crabs","text":"According to a new UN treaty, ______ now qualifies as a weapon of mass destruction.","icon":"wrench","id":"bl-4wAA"},{"pick":1,"deck":"crabs","text":"Before I got laid off, I never pictured a career in ______.","icon":"wrench","id":"bl-Ocm5"},{"pick":1,"deck":"crabs","text":"Coming soon from Pixar: \"______\".","icon":"wrench","id":"bl-wVDF"},{"pick":1,"deck":"crabs","text":"Dear Dan Savage, Please help. I am unable to achieve orgasm without ______.","icon":"wrench","id":"bl-WIjy"},{"pick":1,"deck":"crabs","text":"Ever since \"the incident,\" every time I close my eyes, I still see ______.","icon":"wrench","id":"bl-xBR0"},{"pick":1,"deck":"crabs","text":"From the producers of Shark Week... Coming this fall, ______ Week.","icon":"wrench","id":"bl-wKPJ"},{"pick":1,"deck":"crabs","text":"Fuddruckers® is secretly testing a burger made with ______.","icon":"wrench","id":"bl-Do3B"},{"pick":1,"deck":"crabs","text":"Go-Go-Gadget, ______!","icon":"wrench","id":"bl-96l0"},{"pick":1,"deck":"crabs","text":"Hey man, you gonna come check out my shown tonight? My new band is called \"______.\".","icon":"wrench","id":"bl-yh2o"},{"pick":1,"deck":"crabs","text":"How did I get this restraining order?","icon":"wrench","id":"bl-51ky"},{"pick":1,"deck":"crabs","text":"How did I get through college?","icon":"wrench","id":"bl-fCSp"},{"pick":1,"deck":"crabs","text":"How did I hurt my back?","icon":"wrench","id":"bl-eBKa"},{"pick":1,"deck":"crabs","text":"How did I spend my inheritance?","icon":"wrench","id":"bl-JW3G"},{"pick":1,"deck":"crabs","text":"How did my grandparents make it through the Great Depression?","icon":"wrench","id":"bl-Rmd2"},{"pick":1,"deck":"crabs","text":"I am become ______, the destroyer of worlds.","icon":"wrench","id":"bl-QkVr"},{"pick":1,"deck":"crabs","text":"I do declare, in times of distress I have always relied on ______.","icon":"wrench","id":"bl-kLjg"},{"pick":1,"deck":"crabs","text":"I do wish the newspapers hadn't mentioned ______ in grandpa's obituary.","icon":"wrench","id":"bl-8B8c"},{"pick":1,"deck":"crabs","text":"I don't care *what* people say, ______ is *not* a crime.","icon":"wrench","id":"bl-K6dF"},{"pick":1,"deck":"crabs","text":"I quit my job as a bartender the night some jackass left me ______ as a tip.","icon":"wrench","id":"bl-Qbsk"},{"pick":1,"deck":"crabs","text":"I think I need to take Fluffums to puppy training: he has this terrible habit of ______.","icon":"wrench","id":"bl-tcyn"},{"pick":1,"deck":"crabs","text":"I'm so hungry I could eat ______.","icon":"wrench","id":"bl-AOpC"},{"pick":1,"deck":"crabs","text":"If laughter is the best medicine, the second best is ______.","icon":"wrench","id":"bl-Aq9U"},{"pick":1,"deck":"crabs","text":"If you wanna be my lover, you gotta get with ______.","icon":"wrench","id":"bl-sVRC"},{"pick":1,"deck":"crabs","text":"If you want a picture of the future, imagine a boot stamping on ______ — forever.","icon":"wrench","id":"bl-IEC0"},{"pick":1,"deck":"crabs","text":"In a new novel by Nicholas Sparks, a young girl tragically falls in love with ______.","icon":"wrench","id":"bl-mUi5"},{"pick":1,"deck":"crabs","text":"In his final interview, Robin Williams discussed his private battle with ______.","icon":"wrench","id":"bl-4P1h"},{"pick":1,"deck":"crabs","text":"In my opinion, ______ is grounds for justifiable homicide.","icon":"wrench","id":"bl-grzO"},{"pick":1,"deck":"crabs","text":"In Valhalla, it is said that all brave warriors are given ______.","icon":"wrench","id":"bl-Pfgd"},{"pick":1,"deck":"crabs","text":"Like Midas reborn, everything she touches turns to ______.","icon":"wrench","id":"bl-B9O0"},{"pick":1,"deck":"crabs","text":"My psychic warns that my future is filled with ______.","icon":"wrench","id":"bl-GZKB"},{"pick":1,"deck":"crabs","text":"Oh my God! They killed ______! You bastards!","icon":"wrench","id":"bl-qObR"},{"pick":1,"deck":"crabs","text":"Oh, so you think you're too good for us now, little \"Miss ______!\".","icon":"wrench","id":"bl-FWje"},{"pick":1,"deck":"crabs","text":"Old Willy used to be just like you or me, before ______ got ahold of him.","icon":"wrench","id":"bl-V0Zf"},{"pick":1,"deck":"crabs","text":"Ooooooohh yeah, baby you know what I like. Gimmie ______.","icon":"wrench","id":"bl-0WQY"},{"pick":1,"deck":"crabs","text":"Rumor is, Kim Jong-un is executing prisoners with ______.","icon":"wrench","id":"bl-Av6d"},{"pick":1,"deck":"crabs","text":"Scientists have discovered the true cause of autism: ______.","icon":"wrench","id":"bl-YQ4c"},{"pick":1,"deck":"crabs","text":"Sweet, I just got a Groupon for ______.","icon":"wrench","id":"bl-5tXZ"},{"pick":1,"deck":"crabs","text":"Thank you Mario! But ______ is in another castle!","icon":"wrench","id":"bl-Xuci"},{"pick":1,"deck":"crabs","text":"The best part of waking up is ______.","icon":"wrench","id":"bl-zn14"},{"pick":1,"deck":"crabs","text":"The last three items on my \"bucket list\":.","icon":"wrench","id":"bl-HnLd"},{"pick":1,"deck":"crabs","text":"The NSA wants to talk to me about an email I sent out containing these key phrases:.","icon":"wrench","id":"bl-E9m6"},{"pick":1,"deck":"crabs","text":"The restaurant was nice, but I was surprised to see ______ on the menu.","icon":"wrench","id":"bl-dwnT"},{"pick":1,"deck":"crabs","text":"The road to hell is paved with ______.","icon":"wrench","id":"bl-G4dH"},{"pick":1,"deck":"crabs","text":"Today, Amazon.com® received a patent on ______.","icon":"wrench","id":"bl-48T6"},{"pick":1,"deck":"crabs","text":"Tonight on \"My Super Sweet 16,\" Stephani's parents give her ______.","icon":"wrench","id":"bl-RPjD"},{"pick":1,"deck":"crabs","text":"Utah is considering the legalization of ______.","icon":"wrench","id":"bl-tSCP"},{"pick":1,"deck":"crabs","text":"WANTED: a clean, well-lit place for ______.","icon":"wrench","id":"bl-hWyG"},{"pick":1,"deck":"crabs","text":"What *exactly* is up my ass?","icon":"wrench","id":"bl-OZsC"},{"pick":1,"deck":"crabs","text":"What *really* gave Superman his powers?","icon":"wrench","id":"bl-N9DK"},{"pick":1,"deck":"crabs","text":"What do I have rotting away in a storage unit?","icon":"wrench","id":"bl-oVF7"},{"pick":1,"deck":"crabs","text":"What do we want? ______!\n\nWhen do we want it? Now!","icon":"wrench","id":"bl-olDI"},{"pick":1,"deck":"crabs","text":"What made me this way?","icon":"wrench","id":"bl-k7tf"},{"pick":1,"deck":"crabs","text":"What should I be for Halloween?","icon":"wrench","id":"bl-dork"},{"pick":1,"deck":"crabs","text":"What was one of the rejected flavors for Bertie Bott's Every Flavour Beans™?","icon":"wrench","id":"bl-ScFl"},{"pick":1,"deck":"crabs","text":"What will they carve on my tombstone?","icon":"wrench","id":"bl-UWkb"},{"pick":1,"deck":"crabs","text":"What's my safe word?","icon":"wrench","id":"bl-jNlu"},{"pick":1,"deck":"crabs","text":"What's this town's best-kept secret?","icon":"wrench","id":"bl-KHUt"},{"pick":1,"deck":"crabs","text":"When you play the Game Of ______, you win or you die.","icon":"wrench","id":"bl-tpv4"},{"pick":1,"deck":"crabs","text":"While officially still frowned on, ______ is now permitted in the U.S. armed forces.","icon":"wrench","id":"bl-FIzg"},{"pick":1,"deck":"crabs","text":"Who will be first against the wall when the revolution comes?","icon":"wrench","id":"bl-iAsE"},{"pick":1,"deck":"crabs","text":"Who's *really* to blame?","icon":"wrench","id":"bl-Eoz6"},{"pick":1,"deck":"crabs","text":"Why won't anyone sit with me?","icon":"wrench","id":"bl-WXaF"},{"pick":1,"deck":"crabs","text":"Why won't they let me in Chuck E. Cheese's® anymore?","icon":"wrench","id":"bl-2ukJ"},{"pick":1,"deck":"crabs","text":"William Shatner's shocking new autobiography is titled \"______: The Final Frontier.\".","icon":"wrench","id":"bl-tMOQ"},{"pick":1,"deck":"crabs","text":"Yes, it is I, the world's most dangerous supervillain: Baron Von ______!","icon":"wrench","id":"bl-FP9a"},{"pick":1,"deck":"crabs","text":"You have my sword. \"And you have my bow.\" \"And *my* ______!\".","icon":"wrench","id":"bl-W46I"},{"pick":1,"deck":"crabs","text":"You people are sick! There's *nothing* funny about ______.","icon":"wrench","id":"bl-hEFP"}]